semantic_release/__init__.py
semantic_release/__main__.py
semantic_release/ci_checks.py
semantic_release/cli.py
semantic_release/defaults.cfg
semantic_release/dist.py
semantic_release/errors.py
semantic_release/helpers.py
semantic_release/hvcs.py
semantic_release/pre_commit.py
semantic_release/repository.py
semantic_release/settings.py
semantic_release/vcs_helpers.py
semantic_release/changelog/__init__.py
semantic_release/changelog/changelog.py
semantic_release/changelog/compare.py
semantic_release/history/__init__.py
semantic_release/history/logs.py
semantic_release/history/parser_angular.py
semantic_release/history/parser_emoji.py
semantic_release/history/parser_helpers.py
semantic_release/history/parser_scipy.py
semantic_release/history/parser_tag.py
tests/ci_checks/__init__.py
tests/ci_checks/test_bitbucket.py
tests/ci_checks/test_checker.py
tests/ci_checks/test_circle.py
tests/ci_checks/test_frigg.py
tests/ci_checks/test_gitlab.py
tests/ci_checks/test_jenkins.py
tests/ci_checks/test_semaphore.py
tests/ci_checks/test_travis.py
tests/history/__init__.py
tests/history/test_changelog.py
tests/history/test_version.py
tests/history/test_version_bump.py
tests/mocks/__init__.py
tests/mocks/mock_gitlab.py
tests/parsers/__init__.py
tests/parsers/conftest.py
tests/parsers/test_angular.py
tests/parsers/test_emoji.py
tests/parsers/test_helpers.py
tests/parsers/test_scipy.py
tests/parsers/test_tag.py
python_semantic_release_viettel-1.0.0.dist-info/AUTHORS.rst
python_semantic_release_viettel-1.0.0.dist-info/LICENSE
python_semantic_release_viettel-1.0.0.dist-info/METADATA
python_semantic_release_viettel-1.0.0.dist-info/WHEEL
python_semantic_release_viettel-1.0.0.dist-info/entry_points.txt
python_semantic_release_viettel-1.0.0.dist-info/top_level.txt
python_semantic_release_viettel-1.0.0.dist-info/RECORD
