Metadata-Version: 2.1
Name: python-semantic-release-viettel
Version: 1.0.0
Summary: Custom Automatic Semantic Versioning for Python projects
Home-page: http://github.com/relekang/python-semantic-release
Author: congdd4
Author-email: congdd4@viettel.com.vn
License: MIT
Classifier: Programming Language :: Python
Classifier: Programming Language :: Python :: 3
Classifier: Programming Language :: Python :: 3.6
Classifier: Programming Language :: Python :: 3.7
Classifier: Programming Language :: Python :: 3.8
Classifier: Programming Language :: Python :: 3.9
License-File: LICENSE
License-File: AUTHORS.rst
Requires-Dist: click (<9,>=7)
Requires-Dist: click-log (<1,>=0.3)
Requires-Dist: gitpython (<4,>=3.0.8)
Requires-Dist: invoke (<2,>=1.4.1)
Requires-Dist: semver (<3,>=2.10)
Requires-Dist: twine (<4,>=3)
Requires-Dist: requests (<3,>=2.25)
Requires-Dist: wheel
Requires-Dist: python-gitlab (<4,>=2)
Requires-Dist: tomlkit (<0.11.0,>=0.10.0)
Requires-Dist: dotty-dict (<2,>=1.3.0)
Requires-Dist: dataclasses (==0.8) ; python_version < "3.7.0"
Provides-Extra: dev
Requires-Dist: tox ; extra == 'dev'
Requires-Dist: isort ; extra == 'dev'
Requires-Dist: black ; extra == 'dev'
Provides-Extra: docs
Requires-Dist: Sphinx (==1.3.6) ; extra == 'docs'
Provides-Extra: mypy
Requires-Dist: mypy ; extra == 'mypy'
Requires-Dist: types-requests ; extra == 'mypy'
Provides-Extra: test
Requires-Dist: coverage (<6,>=5) ; extra == 'test'
Requires-Dist: pytest (<6,>=5) ; extra == 'test'
Requires-Dist: pytest-xdist (<2,>=1) ; extra == 'test'
Requires-Dist: pytest-mock (<3,>=2) ; extra == 'test'
Requires-Dist: responses (==0.13.3) ; extra == 'test'
Requires-Dist: mock (==1.3.0) ; extra == 'test'
